sqpax/archive.py
sqpax/sqp.py
sqpax/utils.py
sqpax-0.0.0.dist-info/METADATA
sqpax-0.0.0.dist-info/WHEEL
sqpax-0.0.0.dist-info/top_level.txt
sqpax-0.0.0.dist-info/RECORD
