Metadata-Version: 2.4
Name: sqpax
Version: 0.0.0
Summary: solving sqp trajectory optimization problems with jax
Author: Karen Leung
Author-email: kymleung@uw.edu
Requires-Dist: jax
Requires-Dist: numpy
Requires-Dist: equinox
Requires-Dist: qpax
Requires-Dist: dynamaxsys
Requires-Dist: matplotlib
Dynamic: author
Dynamic: author-email
Dynamic: requires-dist
Dynamic: summary
